{
  "translation": {
    "RAW_MATERIAL": {
      "APPLY_FILTER": "フィルターを適用",
      "FILTER": "フィルター",
      "SELECT_ALL": "全選択",
      "DESELECT": "選択解除",
      "START_DATE": "開始　～",
      "END_DATE": "～　終了",
      "UPLOAD_DESTINATION": "公開期間",
      "PUBLICATION_PERIOD": "公開期間",
      "VIDEO_STATUS": "ユーザー名",
      "PAGE_TITLE": "素　材",
      "MEDIA_TITLE": "タイトル： コードブルー",
      "MODAL_TITLE": "メッセージ",
      "MODAL_BODY_TEXT": "ニューズクラウドへのアップロードが完了しました。\nつづいてビデオプラットフォームへの登録を行いますか？",
      "BUTTON_NO": "いいえ",
      "BUTTON_YES": "はい",
      "VIDEO_UPLOAD_BUTTON":"upload",
      "UPLOAD_VIDEO_TITLE": "Upload Video",
      "VIDEO": "Video",
      "VIDEO_NAME": "Name",
      "VIDEO_THUMBNAIL":"Thumbnail",
      "CANCEL": "Cancel",
      "VIDEO_UPLOAD_CANCEL_MESSAGE": "Cancel video upload",
      "NAME_ERROR" : "Please enter a video name",
      "VIDEO_TYPE_ERROR" : "Please select avi ,mov, mpeg 4,mp4 formatted video",
      "VIDEO_SIZE_ERROR" : "Please select less than 128GB video file size.",
      "SELECT_VIDEO_FILE" :"Please select video file"
    },
    "VIDEO_MANAGE" : {
      "CHANNEL" : "チャンネル",
      "CATEGORY" : "カテゴリ",
      "TITLE" : "タイトル",
      "EXPLANATION" : "説明",
      "TAG" : "タグ（キーワード）",
      "PROFITABLE" : "削　除",
      "UPDATE" : "アップデート",
      "DELETE" : "取　得",
      "STATUS" : "ステータス",
      "COMING_SOON" : "公開予定",
      "EMBED_CODE" : "埋め込みコード",
      "THUMBNAIL" : "サムネイル",
      "LOAD" : "ロード",
      "NO_IMAGE" : "No Image",
      "PUBLISHING_SETTINGS" : "公開設定",
      "CONFIGURATION" : "設定",
      "START" : "開始：",
      "VIEWING_RANGE" : "視聴範囲：",
      "ALLOW_COMMENT" : "コメント許可：",
      "PRIVACY_SETTINGS" : "プライバシー設定：",
      "EDIT" : "編集"
    },
    "CONTENT" : {
      "PAGE_TITLE": "コンテンツ",
      "TAB_EDIT" : "編集",
      "TAB_APPROVAL" : "承認",
      "TAB_RELEASE" : "公開",
      "TITLE" : " タイトル: ",
      "DELIVERY_DESTINATION" : " 配信先:  ",
      "DATA_NOT_FOUND": "データが見つかりません"
    }
  }
}